LICENSE
MANIFEST.in
flask_mail.py
setup.py
tests.py
Flask_Mail.egg-info/PKG-INFO
Flask_Mail.egg-info/SOURCES.txt
Flask_Mail.egg-info/dependency_links.txt
Flask_Mail.egg-info/not-zip-safe
Flask_Mail.egg-info/requires.txt
Flask_Mail.egg-info/top_level.txt
docs/Makefile
docs/conf.py
docs/index.rst
docs/make.bat
docs/_static/flask-mail.jpg
docs/_static/flask-mail.png
docs/_themes/.gitignore
docs/_themes/LICENSE
docs/_themes/README
docs/_themes/flask_theme_support.py
docs/_themes/flask/layout.html
docs/_themes/flask/relations.html
docs/_themes/flask/theme.conf
docs/_themes/flask/static/flasky.css_t
docs/_themes/flask/static/small_flask.css
docs/_themes/flask_small/layout.html
docs/_themes/flask_small/theme.conf
docs/_themes/flask_small/static/flasky.css_t