Metadata-Version: 1.0
Name: Flask-Mail
Version: 0.7.1
Summary: Flask extension for sending email
Home-page: https://github.com/rduplain/flask-mail
Author: Ron DuPlain
Author-email: ron.duplain@gmail.com
License: BSD
Platform: any
Classifier: Development Status :: 4 - Beta
Classifier: Environment :: Web Environment
Classifier: Intended Audience :: Developers
Classifier: License :: OSI Approved :: BSD License
Classifier: Operating System :: OS Independent
Classifier: Programming Language :: Python
Classifier: Topic :: Internet :: WWW/HTTP :: Dynamic Content
Classifier: Topic :: Software Development :: Libraries :: Python Modules
